jarvis_meme_generator/__init__.py
jarvis_meme_generator/static/jarvis.png
jarvis_meme_generator-1.0.4.dist-info/licenses/LICENSE
jarvis_meme_generator-1.0.4.dist-info/METADATA
jarvis_meme_generator-1.0.4.dist-info/WHEEL
jarvis_meme_generator-1.0.4.dist-info/entry_points.txt
jarvis_meme_generator-1.0.4.dist-info/top_level.txt
jarvis_meme_generator-1.0.4.dist-info/RECORD
