Metadata-Version: 2.4
Name: jarvis-meme-generator
Version: 1.0.4
Summary: Generate Jarvis meme images with custom text
Home-page: https://github.com/jbejjani2022/jarvis-meme-generator
Author: Joey Bejjani
Author-email: Joey Bejjani <jbejjani2022@gmail.com>
License: MIT
Project-URL: Homepage, https://github.com/yourusername/jarvis-meme-generator
Project-URL: Repository, https://github.com/yourusername/jarvis-meme-generator
Project-URL: Issues, https://github.com/yourusername/jarvis-meme-generator/issues
Classifier: Development Status :: 4 - Beta
Classifier: Intended Audience :: End Users/Desktop
Classifier: License :: OSI Approved :: MIT License
Classifier: Operating System :: OS Independent
Classifier: Programming Language :: Python :: 3
Classifier: Programming Language :: Python :: 3.7
Classifier: Programming Language :: Python :: 3.8
Classifier: Programming Language :: Python :: 3.9
Classifier: Programming Language :: Python :: 3.10
Classifier: Programming Language :: Python :: 3.11
Requires-Python: >=3.7
License-File: LICENSE
Requires-Dist: Pillow>=8.0.0
Dynamic: author
Dynamic: home-page
Dynamic: license-file
Dynamic: requires-python
